cli/__init__.py
cli/cli.py
somnus/__init__.py
somnus/models.py
somnus/preprocess_audio.py
somnus/somnus.py
somnus/utils.py
somnus-0.2.2.dist-info/LICENSE
somnus-0.2.2.dist-info/METADATA
somnus-0.2.2.dist-info/WHEEL
somnus-0.2.2.dist-info/entry_points.txt
somnus-0.2.2.dist-info/top_level.txt
somnus-0.2.2.dist-info/RECORD
