Metadata-Version: 2.1
Name: somnus
Version: 0.2.2
Summary: Somnus is keyword detection made easy.
Home-page: https://github.com/Skuldur/somnus
Author: Sigurður Skúli Sigurgeirsson
Author-email: siggiskuli@gmail.com
License: UNKNOWN
Platform: UNKNOWN
Classifier: Programming Language :: Python :: 3
Classifier: Programming Language :: Python :: 3.6
Classifier: License :: OSI Approved :: MIT License
Classifier: Operating System :: OS Independent
Requires-Python: >=3.6
Requires-Dist: numpy (>=1.16.2)
Requires-Dist: pydub (>=0.23.1)
Requires-Dist: pyaudio (>=0.2.11)
Requires-Dist: librosa (>=0.8.0)
Requires-Dist: tensorflow (>=2.2.0)
Requires-Dist: fire (>=0.3.1)
Requires-Dist: tqdm (>=4.47.0)
